EphemSahabatFalak/KiraanWaktuSolat.py
EphemSahabatFalak/Takwim_Madinah_Awal_Bulan_Mabims2021.csv
EphemSahabatFalak/Tarikh_Hijri_Awal_Tahun_Pulau_Pinang.csv
EphemSahabatFalak/__init__.py
EphemSahabatFalak-0.1.5.dist-info/METADATA
EphemSahabatFalak-0.1.5.dist-info/WHEEL
EphemSahabatFalak-0.1.5.dist-info/top_level.txt
EphemSahabatFalak-0.1.5.dist-info/RECORD
