Metadata-Version: 2.1
Name: EphemSahabatFalak
Version: 0.1.5
Summary: Sebuah pakej yang boleh menghasilkan pelbagai data berkenaan falak
Author: cartcosine (izzatzubir)
Author-email: <cart.cosine.0x@icloud.com>
Keywords: falak,solat,hilal,waktu,matahari,bulan,kiblat
Classifier: Development Status :: 1 - Planning
Classifier: Intended Audience :: Developers
Classifier: Programming Language :: Python :: 3
Classifier: Operating System :: Unix
Classifier: Operating System :: MacOS :: MacOS X
Classifier: Operating System :: Microsoft :: Windows
Requires-Dist: skyfield
Requires-Dist: pytz
Requires-Dist: datetime
Requires-Dist: DateTime
Requires-Dist: mpmath
Requires-Dist: pandas
Requires-Dist: timezonefinder
Requires-Dist: matplotlib
Requires-Dist: numpy
Requires-Dist: geopandas
Requires-Dist: geodatasets
